Metadata-Version: 1.0
Name: functional
Version: 0.6
Summary: Tools for functional programming in python
Home-page: http://oakwinter.com/code/functional/
Author: Collin Winter
Author-email: collinw@gmail.com
License: PSF License
Keywords: python functional higher-order
Platform: UNKNOWN
Classifier: Intended Audience :: Developers
Classifier: License :: OSI Approved :: PSF License
Classifier: Natural Language :: English
Classifier: Operating System :: OS Independent
Classifier: Programming Language :: Python
Classifier: Topic :: Software Development :: Libraries :: Python Modules
